vaultedb/__init__.py
vaultedb/cli.py
vaultedb/config.py
vaultedb/crypto.py
vaultedb/encrypted_storage.py
vaultedb/errors.py
vaultedb/logging.py
vaultedb/storage.py
vaultedb-1.0.0.dist-info/LICENSE
vaultedb-1.0.0.dist-info/METADATA
vaultedb-1.0.0.dist-info/WHEEL
vaultedb-1.0.0.dist-info/entry_points.txt
vaultedb-1.0.0.dist-info/RECORD
