Metadata-Version: 2.3
Name: vaultedb
Version: 1.0.0
Summary: Encrypted document DB for Python developers. Like SQLite, but with built-in trust, end-to-end encryption, and a zero-config CLI.
License: MIT
Keywords: encryption,database,secure,document store,vaultedb
Author: Python-David
Author-email: mrnwobodo@gmail.com
Requires-Python: >=3.9.2,<4.0
Classifier: Development Status :: 4 - Beta
Classifier: Environment :: Console
Classifier: Intended Audience :: Developers
Classifier: License :: OSI Approved :: MIT License
Classifier: Operating System :: OS Independent
Classifier: Programming Language :: Python :: 3
Classifier: Programming Language :: Python :: 3.10
Classifier: Programming Language :: Python :: 3.11
Classifier: Programming Language :: Python :: 3.12
Classifier: Programming Language :: Python :: 3.13
Classifier: Programming Language :: Python :: 3.8
Classifier: Topic :: Database
Classifier: Topic :: Security :: Cryptography
Requires-Dist: cryptography (>=44.0.3,<45.0.0)
Project-URL: Homepage, https://github.com/Python-David/vaultedb
Project-URL: Repository, https://github.com/Python-David/vaultedb
